{
  "symbol": "BONK/USDT",
  "timeframe": "1h",
  "direction": "LONG",
  "confidence": 0.3686790548297011,
  "ai_score": 0,
  "ta_strength": 0,
  "signal_strength": 0,
  "whale_score": 0,
  "social_score": 0.0,
  "news_score": 0.0,
  "whale_direction_score": 0.0,
  "breakout_probability": 0,
  "entry_price": 2.92e-05,
  "current_price": 2.92e-05,
  "take_profit": 2.993e-05,
  "stop_loss": 2.8762e-05,
  "support_level": 2.861819e-05,
  "resistance_level": 3.0079649999999996e-05,
  "target_time_hours": 24.0,
  "predicted_breakout_threshold": 0.025,
  "predicted_breakout_time_hours": 30.6,
  "timestamp": "2025-07-16 00:28:52.749624",
  "status": "ACTIVE",
  "success_metrics": "{}",
  "confidence_level": 0,
  "volume_score": 0.2,
  "pattern_score": 0.5,
  "momentum_score": 0.5,
  "order_book_imbalance": -0.21167648213024717,
  "top_bid_walls": "[{\"price\": 2.891e-05, \"amount\": 6298179129.0}, {\"price\": 2.877e-05, \"amount\": 3768694473.0}, {\"price\": 2.85e-05, \"amount\": 1630260822.0}]",
  "top_ask_walls": "[{\"price\": 2.941e-05, \"amount\": 10284897719.0}, {\"price\": 2.945e-05, \"amount\": 7979787496.0}, {\"price\": 3e-05, \"amount\": 5151304162.0}]",
  "market_regime": "unknown",
  "regime_note": ""
}