{
  "symbol": "AAVE/USDT",
  "timeframe": "1h",
  "direction": "LONG",
  "ai_score": 0.687,
  "ta_strength": 0.467,
  "signal_strength": 0.467,
  "whale_score": 0.0,
  "social_score": 0.0,
  "news_score": 0.0,
  "current_price": 316.65,
  "entry_price": 316.65,
  "timestamp": "2025-07-14 20:53:58.310983",
  "predicted_gain": 5.0,
  "predicted_duration": "4-8 saat",
  "quality_score": 0.507,
  "quality_checks_passed": true,
  "confidence": 0.372,
  "feature_dummy_ratio": 0.0,
  "feature_quality_warning": false,
  "dynamic_strictness": 0.5,
  "strictness_level": "DÜŞÜK SIKILIK",
  "dynamic_min_confidence": 0.5,
  "dynamic_min_ai_score": 0.4,
  "dynamic_min_ta_strength": 0.35,
  "strictness_recommendation": "Daha fazla sinyal - Düşük sıkılık, fırsat odaklı",
  "volume_score": 0.2,
  "momentum_score": 0.367,
  "pattern_score": 0.0,
  "pattern_score_vs_avg": 1.0,
  "whale_direction_score": 0.0,
  "order_book_imbalance": -0.00029395708214942736,
  "top_bid_walls": "[{\"price\": 316.16, \"amount\": 64.249}, {\"price\": 316.0, \"amount\": 63.451}, {\"price\": 316.4, \"amount\": 55.592}]",
  "top_ask_walls": "[{\"price\": 316.9, \"amount\": 56.446}, {\"price\": 316.86, \"amount\": 51.153}, {\"price\": 317.47, \"amount\": 46.431}]",
  "target_time_hours": 4
}