{
  "symbol": "BCH/USDT",
  "timeframe": "1h",
  "direction": "LONG",
  "ai_score": 0.692,
  "ta_strength": 0.467,
  "signal_strength": 0.467,
  "whale_score": 0.0,
  "social_score": 0.0,
  "news_score": 0.0,
  "current_price": 505.2,
  "entry_price": 505.2,
  "timestamp": "2025-07-14 20:53:20.090533",
  "predicted_gain": 5.0,
  "predicted_duration": "4-8 saat",
  "quality_score": 0.509,
  "quality_checks_passed": true,
  "confidence": 0.37,
  "feature_dummy_ratio": 0.0,
  "feature_quality_warning": false,
  "dynamic_strictness": 0.5,
  "strictness_level": "DÜŞÜK SIKILIK",
  "dynamic_min_confidence": 0.5,
  "dynamic_min_ai_score": 0.4,
  "dynamic_min_ta_strength": 0.35,
  "strictness_recommendation": "Daha fazla sinyal - Düşük sıkılık, fırsat odaklı",
  "volume_score": 0.2,
  "momentum_score": 0.3,
  "pattern_score": 0.0,
  "pattern_score_vs_avg": 1.0,
  "whale_direction_score": 0.0,
  "order_book_imbalance": -0.0009310489827906273,
  "top_bid_walls": "[{\"price\": 499.6, \"amount\": 134.804}, {\"price\": 498.1, \"amount\": 116.725}, {\"price\": 499.4, \"amount\": 112.056}]",
  "top_ask_walls": "[{\"price\": 511.3, \"amount\": 141.056}, {\"price\": 512.9, \"amount\": 121.363}, {\"price\": 510.5, \"amount\": 106.711}]",
  "target_time_hours": 4
}