{
  "symbol": "BTC/USDT",
  "timeframe": "1h",
  "direction": "LONG",
  "ai_score": 0.79,
  "ta_strength": 0.467,
  "signal_strength": 0.467,
  "whale_score": 0.0,
  "social_score": 0.0,
  "news_score": 0.0,
  "current_price": 119462.92,
  "entry_price": 119462.92,
  "timestamp": "2025-07-14 19:11:26.643507",
  "predicted_gain": 5.0,
  "predicted_duration": "4-8 saat",
  "quality_score": 0.558,
  "quality_checks_passed": true,
  "confidence": 0.612,
  "feature_dummy_ratio": 0.0,
  "feature_quality_warning": false,
  "dynamic_strictness": 0.5,
  "strictness_level": "DÜŞÜK SIKILIK",
  "dynamic_min_confidence": 0.5,
  "dynamic_min_ai_score": 0.4,
  "dynamic_min_ta_strength": 0.35,
  "strictness_recommendation": "Daha fazla sinyal - Düşük sıkılık, fırsat odaklı",
  "volume_score": 0.2,
  "momentum_score": 0.367,
  "pattern_score": 0.0,
  "pattern_score_vs_avg": 1.0,
  "whale_direction_score": 0.0,
  "order_book_imbalance": -0.8269847453245097,
  "top_bid_walls": "[{\"price\": 119442.27, \"amount\": 0.59556}, {\"price\": 119461.44, \"amount\": 0.58574}, {\"price\": 119449.83, \"amount\": 0.36554}]",
  "top_ask_walls": "[{\"price\": 119500.0, \"amount\": 20.69902}, {\"price\": 119499.98, \"amount\": 6.72186}, {\"price\": 119461.45, \"amount\": 4.92405}]",
  "target_time_hours": 5
}